mfcondeprimeiropacote/__init__.py
mfcondeprimeiropacote/core.py
mfcondeprimeiropacote_package-1.0.0.dist-info/METADATA
mfcondeprimeiropacote_package-1.0.0.dist-info/WHEEL
mfcondeprimeiropacote_package-1.0.0.dist-info/top_level.txt
mfcondeprimeiropacote_package-1.0.0.dist-info/RECORD
